converterpy/__init__.py
converterpy/version.py
converterpy/adapter/__init__.py
converterpy/cli/__init__.py
converterpy/converter/__init__.py
converterpy/converter/quantity_based_converter.py
converterpy/converter/timestamp_date_converter.py
converterpy/converter/si/__init__.py
converterpy/converter/si/length_converter.py
converterpy/converter/si/mass_converter.py
converterpy/converter/si/time_converter.py
converterpy/exception/__init__.py
converterpy/main/__init__.py
converterpy/main/convert.py
converterpy/provider/__init__.py
converterpy/provider/builtin.py
converterpy/unit/__init__.py
converterpy/unit/quantityunit.py
converterpy/util/__init__.py
converterpy/util/assertion.py
converterpy/util/import__.py
converterpy/util/logger.py
converterpy-1.0.0.dist-info/METADATA
converterpy-1.0.0.dist-info/WHEEL
converterpy-1.0.0.dist-info/entry_points.txt
converterpy-1.0.0.dist-info/top_level.txt
converterpy-1.0.0.dist-info/RECORD
