Metadata-Version: 2.1
Name: converterpy
Version: 1.0.0
Summary: customizable converter tool to convert <source> to <target>
Home-page: https://github.com/bilalekremharmansa/converterpy
Author: Bilal Ekrem Harmansa
Author-email: bilalekremharmansa@gmail.com
License: UNKNOWN
Platform: UNKNOWN
Classifier: Programming Language :: Python :: 3
Classifier: License :: OSI Approved :: MIT License
Classifier: Operating System :: OS Independent
Requires-Python: >=3.5
Requires-Dist: docopt
